shadow4/__init__.py
shadow4/beam/__init__.py
shadow4/beam/s4_beam.py
shadow4/beam/tmp.py
shadow4/beamline/__init__.py
shadow4/beamline/s4_beamline.py
shadow4/beamline/s4_beamline_element.py
shadow4/beamline/s4_beamline_element_movements.py
shadow4/beamline/s4_optical_element_decorators.py
shadow4/beamline/tmp0.py
shadow4/beamline/tmp1.py
shadow4/beamline/optical_elements/__init__.py
shadow4/beamline/optical_elements/absorbers/__init__.py
shadow4/beamline/optical_elements/absorbers/s4_screen.py
shadow4/beamline/optical_elements/absorbers/tmp.py
shadow4/beamline/optical_elements/crystals/8crystals_collimatedsource_case1.py
shadow4/beamline/optical_elements/crystals/8crystals_collimatedsource_case2.py
shadow4/beamline/optical_elements/crystals/__init__.py
shadow4/beamline/optical_elements/crystals/s4_additional_numerical_mesh_crystal.py
shadow4/beamline/optical_elements/crystals/s4_conic_crystal.py
shadow4/beamline/optical_elements/crystals/s4_crystal.py
shadow4/beamline/optical_elements/crystals/s4_ellipsoid_crystal.py
shadow4/beamline/optical_elements/crystals/s4_hyperboloid_crystal.py
shadow4/beamline/optical_elements/crystals/s4_numerical_mesh_crystal.py
shadow4/beamline/optical_elements/crystals/s4_paraboloid_crystal.py
shadow4/beamline/optical_elements/crystals/s4_plane_crystal.py
shadow4/beamline/optical_elements/crystals/s4_sphere_crystal.py
shadow4/beamline/optical_elements/crystals/s4_toroid_crystal.py
shadow4/beamline/optical_elements/crystals/tmp.py
shadow4/beamline/optical_elements/gratings/__init__.py
shadow4/beamline/optical_elements/gratings/s4_additional_numerical_mesh_grating.py
shadow4/beamline/optical_elements/gratings/s4_conic_grating.py
shadow4/beamline/optical_elements/gratings/s4_ellipsoid_grating.py
shadow4/beamline/optical_elements/gratings/s4_grating.py
shadow4/beamline/optical_elements/gratings/s4_hyperboloid_grating.py
shadow4/beamline/optical_elements/gratings/s4_numerical_mesh_grating.py
shadow4-0.1.75.dist-info/licenses/LICENSE
shadow4-0.1.75.dist-info/METADATA
shadow4-0.1.75.dist-info/WHEEL
shadow4-0.1.75.dist-info/top_level.txt
shadow4-0.1.75.dist-info/RECORD
