Metadata-Version: 2.4
Name: shadow4
Version: 0.1.75
Summary: shadow implementation in python
Home-page: https://github.com/oasys-kit/shadow4/
Download-URL: https://github.com/oasys-kit/shadow4/
Author: Manuel Sanchez del Rio, Luca Rebuffi
Author-email: srio@esrf.eu
License-File: LICENSE
Requires-Dist: setuptools
Requires-Dist: numpy
Requires-Dist: scipy
Requires-Dist: syned>=1.0.47
Requires-Dist: srxraylib>=1.0.61
Requires-Dist: crystalpy>=0.0.25
Dynamic: author
Dynamic: author-email
Dynamic: description
Dynamic: description-content-type
Dynamic: download-url
Dynamic: home-page
Dynamic: license-file
Dynamic: requires-dist
Dynamic: summary
